telegram_notification/__init__.py
telegram_notification/__main__.py
telegram_notification/config.ini
telegram_notification/noti
telegram_notification/sample.py
telegram_notification/telegram_notification.py
telegram_notification-0.2.0.data/scripts/config.ini
telegram_notification-0.2.0.data/scripts/noti
telegram_notification-0.2.0.dist-info/METADATA
telegram_notification-0.2.0.dist-info/WHEEL
telegram_notification-0.2.0.dist-info/top_level.txt
telegram_notification-0.2.0.dist-info/RECORD
