Metadata-Version: 2.1
Name: telegram-notification
Version: 0.2.0
Summary: Powerful utility to send telegram alarms from cli
Home-page: https://github.com/dankernel/telegram_notification
Author: dankernel
Author-email: dkdkernel@gmail.com
License: UNKNOWN
Platform: UNKNOWN
Classifier: Programming Language :: Python :: 3
Classifier: License :: OSI Approved :: MIT License
Classifier: Operating System :: OS Independent
Requires-Python: >=3.6
Requires-Dist: python-telegram-bot
